benchmarks/retrieval/retrieve.py
benchmarks/retrieval/retrieve_kaggle.py
sage/__init__.py
sage/chat.py
sage/chunker.py
sage/code_symbols.py
sage/config.py
sage/constants.py
sage/data_manager.py
sage/embedder.py
sage/github.py
sage/index.py
sage/llm.py
sage/reranker.py
sage/retriever.py
sage/sample-exclude.txt
sage/vector_store.py
sage/configs/local.yaml
sage/configs/remote.yaml
tests/__init__.py
tests/conftest.py
tests/test_chunker.py
tests/test_data_manager.py
tests/test_github.py
tests/test_vector_store.py
storia_sage-0.1.0.dist-info/LICENSE
storia_sage-0.1.0.dist-info/METADATA
storia_sage-0.1.0.dist-info/WHEEL
storia_sage-0.1.0.dist-info/entry_points.txt
storia_sage-0.1.0.dist-info/top_level.txt
storia_sage-0.1.0.dist-info/RECORD
