Metadata-Version: 2.1
Name: storia-sage
Version: 0.1.0
Summary: A library to index a code repository and chat with it via LLMs.
Author-email: Julia Turc <founders@storia.ai>
Classifier: Programming Language :: Python :: 3
Classifier: License :: OSI Approved :: MIT License
Classifier: Operating System :: OS Independent
Requires-Python: <=3.11,>=3.9
License-File: LICENSE
Requires-Dist: GitPython==3.1.43
Requires-Dist: Pygments==2.18.0
Requires-Dist: anytree==2.12.1
Requires-Dist: cohere==5.9.2
Requires-Dist: configargparse
Requires-Dist: faiss-cpu==1.9.0
Requires-Dist: fastapi==0.112.2
Requires-Dist: google-ai-generativelanguage==0.6.6
Requires-Dist: gradio>=4.26.0
Requires-Dist: langchain==0.2.16
Requires-Dist: langchain-anthropic==0.1.23
Requires-Dist: langchain-cohere==0.2.4
Requires-Dist: langchain-community==0.2.17
Requires-Dist: langchain-core==0.2.41
Requires-Dist: langchain-experimental==0.0.65
Requires-Dist: langchain-google-genai
Requires-Dist: langchain-nvidia-ai-endpoints==0.2.2
Requires-Dist: langchain-ollama==0.1.3
Requires-Dist: langchain-openai==0.1.25
Requires-Dist: langchain-text-splitters==0.2.4
Requires-Dist: langchain-voyageai==0.1.1
Requires-Dist: langchain-milvus==0.1.6
Requires-Dist: langchain-chroma==0.1.4
Requires-Dist: langchain-qdrant==0.1.4
Requires-Dist: marqo==3.7.0
Requires-Dist: nbformat==5.10.4
Requires-Dist: openai==1.42.0
Requires-Dist: pinecone==5.0.1
Requires-Dist: pinecone-text==0.9.0
Requires-Dist: python-dotenv==1.0.1
Requires-Dist: python-Levenshtein==0.26.0
Requires-Dist: requests==2.32.3
Requires-Dist: semchunk==2.2.0
Requires-Dist: sentence-transformers==3.1.0
Requires-Dist: tenacity==8.5.0
Requires-Dist: tiktoken==0.7.0
Requires-Dist: tokenizers==0.19.1
Requires-Dist: transformers==4.44.2
Requires-Dist: tree-sitter==0.22.3
Requires-Dist: tree-sitter-typescript==0.21.2
Requires-Dist: tree-sitter-language-pack==0.2.0
Requires-Dist: voyageai==0.2.3
Requires-Dist: setuptools
Provides-Extra: dev
Requires-Dist: black; extra == "dev"
